CGFCore/BayesianGameFile.py
CGFCore/ComposedGameFile.py
CGFCore/GameFile.py
CGFCore/ImperfectInformationGame.py
CGFCore/NonZeroSumGameFile.py
CGFCore/SequentialGameFile.py
CGFCore/StochasticGameFile.py
CGFCore/ZeroSumGameFile.py
CGFCore/__init__.py
CGFCore/main.py
CGFCore/games/PrisonersDilemmaGame.py
CGFCore/games/__init__.py
CGFCore/games/variant1.py
CGFCore/games/variant2.py
CGFCore/games/variant3.py
CGFCore/games/variant4.py
CGFCore/games/variant5.py
CGFCore/opengameframework/OpenGames.py
CGFCore/opengameframework/__init__.py
CGFCore/opengameframework/deterministic.py
CGFCore/opengameframework/final.py
CGFCore/opengameframework/stochasticity.py
CGFCore/test/__init__.py
CGFCore/test/evaluate.py
CGF-0.0.7.dist-info/LICENSE.txt
CGF-0.0.7.dist-info/METADATA
CGF-0.0.7.dist-info/WHEEL
CGF-0.0.7.dist-info/top_level.txt
CGF-0.0.7.dist-info/RECORD
